vaspflow/__init__.py
vaspflow/core.py
vaspflow-0.1.1.dist-info/licenses/LICENSE
vaspflow-0.1.1.dist-info/METADATA
vaspflow-0.1.1.dist-info/WHEEL
vaspflow-0.1.1.dist-info/entry_points.txt
vaspflow-0.1.1.dist-info/top_level.txt
vaspflow-0.1.1.dist-info/RECORD
