Metadata-Version: 2.4
Name: vaspflow
Version: 0.1.1
Summary: VASP Workflow Automation and Band Structure Analysis Tool
Home-page: https://github.com/ooteki-teo/vaspflow
Author: Dinghui Wang
Author-email: wangdh@cumt.edu.cn
Keywords: vasp,dft,band-structure,materials-science
Classifier: Programming Language :: Python :: 3
Classifier: Programming Language :: Python :: 3.6
Classifier: Programming Language :: Python :: 3.7
Classifier: Programming Language :: Python :: 3.8
Classifier: Programming Language :: Python :: 3.9
Classifier: License :: OSI Approved :: MIT License
Classifier: Operating System :: OS Independent
Classifier: Topic :: Scientific/Engineering :: Physics
Classifier: Topic :: Scientific/Engineering :: Chemistry
Requires-Python: >=3.6
License-File: LICENSE
Requires-Dist: numpy>=1.15.0
Requires-Dist: matplotlib>=2.0.0
Dynamic: author
Dynamic: author-email
Dynamic: classifier
Dynamic: description
Dynamic: description-content-type
Dynamic: home-page
Dynamic: keywords
Dynamic: license-file
Dynamic: requires-dist
Dynamic: requires-python
Dynamic: summary
